pysharekit-1.0.2.dist-info/licenses/LICENSE
sharer/__init__.py
sharer/__main__.py
sharer/server.py
pysharekit-1.0.2.dist-info/METADATA
pysharekit-1.0.2.dist-info/WHEEL
pysharekit-1.0.2.dist-info/entry_points.txt
pysharekit-1.0.2.dist-info/top_level.txt
pysharekit-1.0.2.dist-info/RECORD
